LICENSE
MANIFEST.in
README.rst
requirements.txt
setup.py
webassets_iife/__init__.py
webassets_iife.egg-info/PKG-INFO
webassets_iife.egg-info/SOURCES.txt
webassets_iife.egg-info/dependency_links.txt
webassets_iife.egg-info/top_level.txt