Metadata-Version: 1.1
Name: webassets-iife
Version: 0.1.0
Summary: IIFE filter for webassets
Home-page: https://github.com/bfontaine/webassets-iife
Author: Baptiste Fontaine
Author-email: b@ptistefontaine.fr
License: Copyright © 2014 – Baptiste Fontaine
